GenPy/__init__.py
GenPy/genpy.py
GenPy_karjakak-0.0.7.dist-info/METADATA
GenPy_karjakak-0.0.7.dist-info/WHEEL
GenPy_karjakak-0.0.7.dist-info/top_level.txt
GenPy_karjakak-0.0.7.dist-info/RECORD
